MANIFEST.in
README.txt
setup.py
HL7py/__init__.py
HL7py/constants.py
HL7py/hl7_test.py
HL7py/hl7fields.py
HL7py/parser.py
HL7py/test_messages.py
HL7py.egg-info/PKG-INFO
HL7py.egg-info/SOURCES.txt
HL7py.egg-info/dependency_links.txt
HL7py.egg-info/not-zip-safe
HL7py.egg-info/top_level.txt