Metadata-Version: 1.0
Name: HL7py
Version: 1.0
Summary: HL7 message parser
Home-page: https://github.com/norlowski/HL7py
Author: Nicholas Orlowski
Author-email: nick.orlowski@gmail.com
License: MIT
Keywords: hl7 parsing
Platform: UNKNOWN
